{
  "issues": [
	  	{
	  	"id" : "001",
	  	"Státusz" : "Bejelentve",
	  	"Bejelentve" : "2018.05.01. 10:12",
	  	"Várható_Kezdés" : "2018.05.02. 10:12",
	  	"Objektum" : "AAA03",
	  	"Ingatlan" : "Kis utca 1.",
	  	"Szakterület" : "Kertészet",
	  	"Típus" : "Igénybejelentés",
	  	"Besorolás" : "Normál",
	  	"Sz_szint" : "Munkaidőben",
	  	"issue" : "UPS hiba"
	  	}, 
	  	{
	  	"id" : "002",
	  	"Státusz" : "Munkafelvétel",
	  	"Bejelentve" : "2018.05.01. 10:12",
	  	"Várható_Kezdés" : "2018.05.01. 12:12",
	  	"Objektum" : "AAA02",
	  	"Ingatlan" : "Nagy utca 1.",
	  	"Szakterület" : "Üzemeltetés",
	  	"Típus" : "Hibabejelentés",
	  	"Besorolás" : "Havária",
	  	"Sz_szint" : "Munkaidőn kívül",
	  	"issue" : "A 4. emeleten megállt a lift."
	  	},
	  	{
	  	"id" : "003",
	  	"Státusz" : "Jóváhagyásra",
	  	"Bejelentve" : "2018.05.01. 10:12",
	  	"Várható_Kezdés" : "2018.05.01. 12:12",
	  	"Objektum" : "AAA02",
	  	"Ingatlan" : "Nagy utca 1.",
	  	"Szakterület" : "Üzemeltetés",
	  	"Típus" : "Hibabejelentés",
	  	"Besorolás" : "Havária",
	  	"Sz_szint" : "Munkaidőn kívül",
	  	"issue" : "Eldugult a lefolyó"
	  	},
	  	{
	  	"id" : "004",
	  	"Státusz" : "Végrehajtásra",
	  	"Bejelentve" : "2018.05.01. 10:12",
	  	"Várható_Kezdés" : "2018.05.01. 12:12",
	  	"Objektum" : "AAA02",
	  	"Ingatlan" : "Nagy utca 4.",
	  	"Szakterület" : "Üzemeltetés",
	  	"Típus" : "Hibabejelentés",
	  	"Besorolás" : "Havária",
	  	"Sz_szint" : "Munkaidőn kívül",
	  	"issue" : "Nem működik a dugalj"
	  	},
	  	{
	  	"id" : "005",
	  	"Státusz" : "TeljesítésIgazolásra",
	  	"Bejelentve" : "2018.05.01. 10:12",
	  	"Várható_Kezdés" : "2018.05.01. 12:12",
	  	"Objektum" : "AAA02",
	  	"Ingatlan" : "Nagy utca 4.",
	  	"Szakterület" : "Üzemeltetés",
	  	"Típus" : "Hibabejelentés",
	  	"Besorolás" : "Havária",
	  	"Sz_szint" : "Munkaidőn kívül",
	  	"issue" : "Nincs áram"
	  	},
	  	{
	  	"id" : "006",
	  	"Státusz" : "Ellenőrzésre",
	  	"Bejelentve" : "2018.05.01. 10:12",
	  	"Várható_Kezdés" : "2018.05.01. 12:12",
	  	"Objektum" : "AAA02",
	  	"Ingatlan" : "Nagy utca 4.",
	  	"Szakterület" : "Üzemeltetés",
	  	"Típus" : "Hibabejelentés",
	  	"Besorolás" : "Havária",
	  	"Sz_szint" : "Munkaidőn kívül",
	  	"issue" : "Nincs gáz"
	  	},
	  	{
	  	"id" : "007",
	  	"Státusz" : "Lezárva",
	  	"Bejelentve" : "2018.05.01. 10:12",
	  	"Várható_Kezdés" : "2018.05.01. 12:12",
	  	"Objektum" : "AAA02",
	  	"Ingatlan" : "Nagy utca 4.",
	  	"Szakterület" : "Üzemeltetés",
	  	"Típus" : "Hibabejelentés",
	  	"Besorolás" : "Havária",
	  	"Sz_szint" : "Munkaidőn kívül",
	  	"issue" : "Nincs meleg víz"
	  	}
	]
}
